mkdocs_boost/nav.html
mkdocs_boost/toc.html
mkdocs_boost/__init__.py
mkdocs_boost/base.html
mkdocs_boost/js/highlight.pack.js
mkdocs_boost/css/boostbook.css
mkdocs_boost/css/reference.css
mkdocs_boost/css/boost.css
mkdocs_boost/css/docutils.css
mkdocs_boost/css/minimal.css
mkdocs_boost/css/styles/far.css
mkdocs_boost/css/styles/atelier-savanna-dark.css
mkdocs_boost/css/styles/solarized-light.css
mkdocs_boost/css/styles/docco.css
mkdocs_boost/css/styles/atelier-sulphurpool-dark.css
mkdocs_boost/css/styles/hybrid.css
mkdocs_boost/css/styles/default.css
mkdocs_boost/css/styles/grayscale.css
mkdocs_boost/css/styles/kimbie.dark.css
mkdocs_boost/css/styles/monokai.css
mkdocs_boost/css/styles/railscasts.css
mkdocs_boost/css/styles/darkula.css
mkdocs_boost/css/styles/dark.css
mkdocs_boost/css/styles/atelier-estuary-dark.css
mkdocs_boost/css/styles/zenburn.css
mkdocs_boost/css/styles/brown-paper.css
mkdocs_boost/css/styles/hopscotch.css
mkdocs_boost/css/styles/xcode.css
mkdocs_boost/css/styles/atelier-seaside-light.css
mkdocs_boost/css/styles/brown-papersq.png
mkdocs_boost/css/styles/rainbow.css
mkdocs_boost/css/styles/school-book.css
mkdocs_boost/css/styles/atelier-heath-dark.css
mkdocs_boost/css/styles/school-book.png
mkdocs_boost/css/styles/tomorrow-night-eighties.css
mkdocs_boost/css/styles/atelier-dune-dark.css
mkdocs_boost/css/styles/tomorrow-night.css
mkdocs_boost/css/styles/obsidian.css
mkdocs_boost/css/styles/atelier-plateau-dark.css
mkdocs_boost/css/styles/atelier-seaside-dark.css
mkdocs_boost/css/styles/color-brewer.css
mkdocs_boost/css/styles/atelier-savanna-light.css
mkdocs_boost/css/styles/github-gist.css
mkdocs_boost/css/styles/arta.css
mkdocs_boost/css/styles/kimbie.light.css
mkdocs_boost/css/styles/agate.css
mkdocs_boost/css/styles/atelier-sulphurpool-light.css
mkdocs_boost/css/styles/tomorrow-night-blue.css
mkdocs_boost/css/styles/arduino-light.css
mkdocs_boost/css/styles/mono-blue.css
mkdocs_boost-0.0.2.dist-info/WHEEL
mkdocs_boost-0.0.2.dist-info/top_level.txt
mkdocs_boost-0.0.2.dist-info/RECORD
mkdocs_boost-0.0.2.dist-info/entry_points.txt
mkdocs_boost-0.0.2.dist-info/DESCRIPTION.rst
mkdocs_boost-0.0.2.dist-info/METADATA
mkdocs_boost-0.0.2.dist-info/metadata.json
