Metadata-Version: 2.0
Name: mkdocs-boost
Version: 0.0.2
Summary: Boost theme for mkdocs
Home-page: https://github.com/pfultz2/mkdocs-boost
Author: Paul Fultz II
Author-email: pfultz2@yahoo.com
License: boost
Platform: UNKNOWN
